DocumentLayoutAnalysis/__init__.py
DocumentLayoutAnalysis-0.0.3.dist-info/METADATA
DocumentLayoutAnalysis-0.0.3.dist-info/WHEEL
DocumentLayoutAnalysis-0.0.3.dist-info/top_level.txt
DocumentLayoutAnalysis-0.0.3.dist-info/RECORD
